[
	{
		"nome": "Yanomami",
		"mark": {
			"coordinates": [ 3.5, -64 ],
			"zoom": 6
		},
		"land": {
			"style": {
				"color": "#FF0000",
				"fillColor": "#FF0000"
			},
			"coordinates": [
				[1.38,	-62.6 ],
				[1.7, -61.5],
				[4,	-62 ],
				[4.1, -62.3],
				[3.7, -62.7],
				[4.2, -64.7],
				[2.4, -64],
				[2.4, -63.4],
				[2.2, -63.3],
				[1.9, -63.9],
				[0.7, -65.4],
				[0,	-65.5 ]
			]
		}
	},
	{
		"nome": "Guarani",
		"mark": {
			"coordinates": [ -24, -55 ],
			"zoom": 4.5
		},
		"land": {
			"style": {
				"color": "#FFFF00",
				"fillColor": "#FFFF00"
			},
			"coordinates": [
				[-22, -44],
				[-25, -48.5],
				[-28.5, -48.5],

				[-33.6,	-53.4 ],
				[-28, -55],
				[-27, -55],
				[-25, -57],
				[-23, -62],
				[-23.3, -62.2],
				[-24.5, -63.5 ],
				[-24.7, -63.5 ],
				[-23, -64.3 ],
				[-19, -63]
			]
		}
	}
]